dora_dhcp_client/__init__.py
dora_dhcp_client/dora.py
dora_dhcp_client-0.1.3.data/scripts/dora.py
dora_dhcp_client-0.1.3.dist-info/LICENSE
dora_dhcp_client-0.1.3.dist-info/METADATA
dora_dhcp_client-0.1.3.dist-info/WHEEL
dora_dhcp_client-0.1.3.dist-info/top_level.txt
dora_dhcp_client-0.1.3.dist-info/RECORD
