Metadata-Version: 2.1
Name: dora-dhcp-client
Version: 0.1.3
Summary: ('A DHCP client designed to be used for troubleshooting of DHCP servers',)
Home-page: https://github.com/vfrazao-ns1/dora_dhcp_client
Author: Victor Frazao
Author-email: 
License: Apache 2.0
Platform: UNKNOWN
Classifier: License :: OSI Approved :: Apache Software License
Classifier: Programming Language :: Python
Classifier: Programming Language :: Python :: 3
Classifier: Programming Language :: Python :: 3.8
Classifier: Programming Language :: Python :: Implementation :: CPython
Requires-Python: >=3.8.0
License-File: LICENSE
Requires-Dist: dhcppython
